lowhaio_chunked.py
lowhaio_chunked-0.0.5.dist-info/LICENSE
lowhaio_chunked-0.0.5.dist-info/METADATA
lowhaio_chunked-0.0.5.dist-info/WHEEL
lowhaio_chunked-0.0.5.dist-info/top_level.txt
lowhaio_chunked-0.0.5.dist-info/RECORD
