Metadata-Version: 2.1
Name: lowhaio-chunked
Version: 0.0.5
Summary: Chunked transfer request encoding for lowhaio
Home-page: https://github.com/michalc/lowhaio-chunked
Author: Michal Charemza
Author-email: michal@charemza.name
License: UNKNOWN
Platform: UNKNOWN
Classifier: Programming Language :: Python :: 3
Classifier: License :: OSI Approved :: MIT License
Classifier: Operating System :: OS Independent
Classifier: Framework :: AsyncIO
Requires-Python: >=3.6.3
